django_drf_otp/__init__.py
django_drf_otp/apps.py
django_drf_otp/enums.py
django_drf_otp/exceptions.py
django_drf_otp/models.py
django_drf_otp/notifiers.py
django_drf_otp/serializers.py
django_drf_otp/services.py
django_drf_otp/settings.py
django_drf_otp/signals.py
django_drf_otp/strategies.py
django_drf_otp/test_settings.py
django_drf_otp/urls.py
django_drf_otp/viewsets.py
django_drf_otp/locale/tr/LC_MESSAGES/django.po
django_drf_otp/migrations/0001_initial.py
django_drf_otp/migrations/0002_populate_notification_preference.py
django_drf_otp/migrations/0003_remove_verificationtoken_expire_date.py
django_drf_otp/migrations/0004_alter_usernotificationpreference_id_and_more.py
django_drf_otp/migrations/0005_verificationtoken_secret_chars_and_more.py
django_drf_otp/migrations/0006_verificationtoken_active_token_idx.py
django_drf_otp/migrations/0007_alter_verificationtoken_secret_chars.py
django_drf_otp/migrations/__init__.py
django_drf_otp/templates/django_drf_otp/email.html
django_drf_otp-0.0.11.dist-info/LICENSE
django_drf_otp-0.0.11.dist-info/METADATA
django_drf_otp-0.0.11.dist-info/WHEEL
django_drf_otp-0.0.11.dist-info/top_level.txt
django_drf_otp-0.0.11.dist-info/RECORD
