Metadata-Version: 2.1
Name: django-drf-otp
Version: 0.0.11
Summary: A Django app to supports 2FA(Two Factor Authentication) on djangorestframework.
Home-page: https://bitbucket.org/akinonteam/django_drf_otp/
Author: Akinon
Author-email: dev@akinon.com
License: MIT
Classifier: Environment :: Web Environment
Classifier: Framework :: Django
Classifier: Framework :: Django :: 4.2
Classifier: Intended Audience :: Developers
Classifier: License :: OSI Approved :: BSD License
Classifier: Operating System :: OS Independent
Classifier: Programming Language :: Python
Classifier: Programming Language :: Python :: 3
Classifier: Programming Language :: Python :: 3 :: Only
Classifier: Topic :: Internet :: WWW/HTTP
Classifier: Topic :: Internet :: WWW/HTTP :: Dynamic Content
Requires-Python: >=3.8
License-File: LICENSE
